CHANGES.txt
LICENSE
MANIFEST.in
README.md
ltcrabbit.py
requirements.txt
setup.py
bin/ltcrabbit-cli
ltcrabbit.egg-info/PKG-INFO
ltcrabbit.egg-info/SOURCES.txt
ltcrabbit.egg-info/dependency_links.txt
ltcrabbit.egg-info/requires.txt
ltcrabbit.egg-info/top_level.txt