Metadata-Version: 1.0
Name: ltcrabbit
Version: 0.2.1
Summary: LTCRabbit.com API wrapper
Home-page: https://github.com/syntaxsugar/ltcrabbit
Author: Jaromir Fojtu
Author-email: jaromir.fojtu@gmail.com
License: BSD
Platform: UNKNOWN
